tiny_rsa/__init__.py
tiny_rsa/tests/__init__.py
tiny_rsa/tests/test.py
tiny_rsa-0.0.1.dist-info/DESCRIPTION.rst
tiny_rsa-0.0.1.dist-info/METADATA
tiny_rsa-0.0.1.dist-info/RECORD
tiny_rsa-0.0.1.dist-info/WHEEL
tiny_rsa-0.0.1.dist-info/metadata.json
tiny_rsa-0.0.1.dist-info/top_level.txt
