Metadata-Version: 2.0
Name: tiny-rsa
Version: 0.0.1
Summary: RSA in pure Python
Home-page: https://github.com/OpenGroper/tiny_rsa
Author: Shuge Lee
Author-email: shuge.lee@gmail.com
License: MIT License
Keywords: rsa
Platform: UNKNOWN
